annoy/__init__.py
annoy/__init__.pyi
annoy/annoylib.cpython-310-darwin.so
annoy/py.typed
annoy-1.17.2.dist-info/LICENSE
annoy-1.17.2.dist-info/METADATA
annoy-1.17.2.dist-info/WHEEL
annoy-1.17.2.dist-info/top_level.txt
annoy-1.17.2.dist-info/RECORD
